gti/__init__.py
gti/client.py
gti/data_packet.py
gti/decoder.py
gti/encoder.py
gti/json_builder.py
gti/parser.py
gti/server.py
gti/utils.py
gti_scnu-0.0.22.dist-info/METADATA
gti_scnu-0.0.22.dist-info/WHEEL
gti_scnu-0.0.22.dist-info/top_level.txt
gti_scnu-0.0.22.dist-info/RECORD
