Metadata-Version: 2.1
Name: gti-scnu
Version: 0.0.22
Summary: The remote control system for the HuaGuangEdu team
Home-page: http://42.192.82.19/
Author: gyanano
Author-email: 1624055384@qq.com
License: GPLv3
Requires-Dist: astor
Requires-Dist: requests
